pangeo_forge_esgf/__init__.py
pangeo_forge_esgf/_version.py
pangeo_forge_esgf/parsing.py
pangeo_forge_esgf/recipe_inputs.py
pangeo_forge_esgf/utils.py
pangeo_forge_esgf/tests/test_logging.py
pangeo_forge_esgf/tests/test_parsing.py
pangeo_forge_esgf/tests/test_recipe_inputs.py
pangeo_forge_esgf/tests/test_utils.py
pangeo_forge_esgf-0.3.1.dist-info/LICENSE
pangeo_forge_esgf-0.3.1.dist-info/METADATA
pangeo_forge_esgf-0.3.1.dist-info/WHEEL
pangeo_forge_esgf-0.3.1.dist-info/top_level.txt
pangeo_forge_esgf-0.3.1.dist-info/RECORD
