Metadata-Version: 2.1
Name: pangeo-forge-esgf
Version: 0.3.1
Summary: Using queries to the ESGF API to generate urls and keyword arguments for receipe generation in pangeo-forge
Author-email: Julius Busecke <julius@ldeo.columbia.edu>
License: Apache-2.0
Project-URL: Homepage, https://github.com/jbusecke/pangeo-forge-esgf
Project-URL: Tracker, https://github.com/jbusecke/pangeo-forge-esgf/issues
Keywords: pangeo,data,esgf
Classifier: Development Status :: 1 - Planning
Classifier: License :: OSI Approved :: Apache Software License
Classifier: Operating System :: OS Independent
Classifier: Intended Audience :: Science/Research
Classifier: Programming Language :: Python
Classifier: Programming Language :: Python :: 3
Classifier: Programming Language :: Python :: 3.9
Classifier: Programming Language :: Python :: 3.10
Classifier: Topic :: Scientific/Engineering
Requires-Python: >=3.9
License-File: LICENSE
Requires-Dist: aiohttp
Requires-Dist: tqdm
Requires-Dist: backoff
Requires-Dist: requests
Provides-Extra: dev
Requires-Dist: ruff ; extra == 'dev'
Requires-Dist: mypy ; extra == 'dev'
Requires-Dist: types-requests ; extra == 'dev'
Requires-Dist: pre-commit ; extra == 'dev'
Requires-Dist: pangeo-forge-esgf[test] ; extra == 'dev'
Provides-Extra: test
Requires-Dist: pytest ; extra == 'test'
